README
setup.cfg
setup.py
aliqat/__init__.py
aliqat/errors.py
aliqat/graphs.py
aliqat.egg-info/PKG-INFO
aliqat.egg-info/SOURCES.txt
aliqat.egg-info/dependency_links.txt
aliqat.egg-info/top_level.txt